alexandria/__init__.py
alexandria/awslib/__init__.py
alexandria/awslib/credential.py
alexandria/awslib/secrets_manager.py
alexandria/galib/__init__.py
alexandria/galib/data.py
alexandria/galib/utils.py
alexandria/s3lib/__init__.py
alexandria/s3lib/credential.py
alexandria/s3lib/dataframe.py
alexandria/s3lib/file.py
fcxai_alexandria-0.2.3.dist-info/METADATA
fcxai_alexandria-0.2.3.dist-info/WHEEL
fcxai_alexandria-0.2.3.dist-info/top_level.txt
fcxai_alexandria-0.2.3.dist-info/RECORD
