Metadata-Version: 2.1
Name: fcxai-alexandria
Version: 0.2.3
Classifier: Programming Language :: Python :: 3
Classifier: Programming Language :: Python :: 3 :: Only
Requires-Python: >=3.8
Requires-Dist: boto3
Requires-Dist: google-analytics-data
Requires-Dist: google-api-python-client
Requires-Dist: joblib
Requires-Dist: oauth2client
Requires-Dist: pandas
Provides-Extra: dev
Requires-Dist: black ; extra == 'dev'
Requires-Dist: ipython ; extra == 'dev'
Requires-Dist: pre-commit ; extra == 'dev'
Requires-Dist: pytest ; extra == 'dev'
